{
  "lastUpdated": "2025-12-07T00:54:14.851839",
  "count": 399,
  "data": {
    "BS1": {
      "code": "BS1",
      "price": 1.003394,
      "date": "1764892800000",
      "fetchedAt": "2025-12-07T00:52:38.787059"
    },
    "LTC": {
      "code": "LTC",
      "price": 1.289063,
      "date": "1764892800000",
      "fetchedAt": "2025-12-07T00:52:38.813957"
    },
    "CVE": {
      "code": "CVE",
      "price": 2.206718,
      "date": "1764892800000",
      "fetchedAt": "2025-12-07T00:52:38.841801"
    },
    "SSO": {
      "code": "SSO",
      "price": 11.313591,
      "date": "1764892800000",
      "fetchedAt": "2025-12-07T00:52:38.854767"
    },
    "PUC": {
      "code": "PUC",
      "price": 5.609116,
      "date": "1764892800000",
      "fetchedAt": "2025-12-07T00:52:38.871580"
    },
    "ANL": {
      "code": "ANL",
      "price": 28.665724,
      "date": "1764892800000",
      "fetchedAt": "2025-12-07T00:52:38.878942"
    },
    "PAL": {
      "code": "PAL",
      "price": 49.29296,
      "date": "1764892800000",
      "fetchedAt": "2025-12-07T00:52:38.878949"
    },
    "PUR": {
      "code": "PUR",
      "price": 7.971109,
      "date": "1764892800000",
      "fetchedAt": "2025-12-07T00:52:38.881748"
    },
    "FUM": {
      "code": "FUM",
      "price": 54.610353,
      "date": "1764892800000",
      "fetchedAt": "2025-12-07T00:52:38.892214"
    },
    "ADP": {
      "code": "ADP",
      "price": 1.205075,
      "date": "1764892800000",
      "fetchedAt": "2025-12-07T00:52:38.907790"
    },
    "AOY": {
      "code": "AOY",
      "price": 0.288048,
      "date": "1764892800000",
      "fetchedAt": "2025-12-07T00:52:38.908737"
    },
    "URG": {
      "code": "URG",
      "price": 65.032943,
      "date": "1764892800000",
      "fetchedAt": "2025-12-07T00:52:38.908741"
    },
    "BHE": {
      "code": "BHE",
      "price": 1.42518,
      "date": "1764892800000",
      "fetchedAt": "2025-12-07T00:52:38.908743"
    },
    "VAY": {
      "code": "VAY",
      "price": 1.359284,
      "date": "1764892800000",
      "fetchedAt": "2025-12-07T00:52:38.908745"
    },
    "AFA": {
      "code": "AFA",
      "price": 0.996034,
      "date": "1764892800000",
      "fetchedAt": "2025-12-07T00:52:38.910682"
    },
    "AFO": {
      "code": "AFO",
      "price": 1.163905,
      "date": "1764892800000",
      "fetchedAt": "2025-12-07T00:52:38.910688"
    },
    "BVC": {
      "code": "BVC",
      "price": 3.331334,
      "date": "1764892800000",
      "fetchedAt": "2025-12-07T00:52:38.910690"
    },
    "AKU": {
      "code": "AKU",
      "price": 0.683724,
      "date": "1764892800000",
      "fetchedAt": "2025-12-07T00:52:38.910692"
    },
    "BUY": {
      "code": "BUY",
      "price": 1.350833,
      "date": "1764892800000",
      "fetchedAt": "2025-12-07T00:52:38.911574"
    },
    "ZFB": {
      "code": "ZFB",
      "price": 5.3059,
      "date": "1764892800000",
      "fetchedAt": "2025-12-07T00:52:38.938824"
    },
    "UCN": {
      "code": "UCN",
      "price": 1.758833,
      "date": "1764892800000",
      "fetchedAt": "2025-12-07T00:52:38.939883"
    },
    "DZS": {
      "code": "DZS",
      "price": 1.192215,
      "date": "1764892800000",
      "fetchedAt": "2025-12-07T00:52:38.942945"
    },
    "KVT": {
      "code": "KVT",
      "price": 1.169645,
      "date": "1764892800000",
      "fetchedAt": "2025-12-07T00:52:38.943429"
    },
    "AKE": {
      "code": "AKE",
      "price": 0.463739,
      "date": "1764892800000",
      "fetchedAt": "2025-12-07T00:52:38.946067"
    },
    "AJN": {
      "code": "AJN",
      "price": 54.706546,
      "date": "1764892800000",
      "fetchedAt": "2025-12-07T00:52:38.946072"
    },
    "DSH": {
      "code": "DSH",
      "price": 1.699275,
      "date": "1764892800000",
      "fetchedAt": "2025-12-07T00:52:38.946074"
    },
    "VCY": {
      "code": "VCY",
      "price": 2.688125,
      "date": "1764892800000",
      "fetchedAt": "2025-12-07T00:52:38.946076"
    },
    "AVZ": {
      "code": "AVZ",
      "price": 90.701068,
      "date": "1764892800000",
      "fetchedAt": "2025-12-07T00:52:38.946078"
    },
    "GUM": {
      "code": "GUM",
      "price": 10.129205,
      "date": "1764892800000",
      "fetchedAt": "2025-12-07T00:52:38.963787"
    },
    "URV": {
      "code": "URV",
      "price": 2.982745,
      "date": "1764892800000",
      "fetchedAt": "2025-12-07T00:52:38.965494"
    },
    "HVV": {
      "code": "HVV",
      "price": 60.205766,
      "date": "1764892800000",
      "fetchedAt": "2025-12-07T00:52:38.977019"
    },
    "HZV": {
      "code": "HZV",
      "price": 5.090333,
      "date": "1764892800000",
      "fetchedAt": "2025-12-07T00:52:38.977025"
    },
    "GMI": {
      "code": "GMI",
      "price": 1.168624,
      "date": "1764892800000",
      "fetchedAt": "2025-12-07T00:52:38.977029"
    },
    "HYY": {
      "code": "HYY",
      "price": 10.354574,
      "date": "1764892800000",
      "fetchedAt": "2025-12-07T00:52:38.977644"
    },
    "GNZ": {
      "code": "GNZ",
      "price": 1.217856,
      "date": "1764892800000",
      "fetchedAt": "2025-12-07T00:52:38.978946"
    },
    "AK3": {
      "code": "AK3",
      "price": 39.088774,
      "date": "1764892800000",
      "fetchedAt": "2025-12-07T00:52:38.980819"
    },
    "PAI": {
      "code": "PAI",
      "price": 5.611348,
      "date": "1764892800000",
      "fetchedAt": "2025-12-07T00:52:38.982774"
    },
    "CVB": {
      "code": "CVB",
      "price": 3.268495,
      "date": "1764892800000",
      "fetchedAt": "2025-12-07T00:52:38.999691"
    },
    "GGC": {
      "code": "GGC",
      "price": 4.34697,
      "date": "1764892800000",
      "fetchedAt": "2025-12-07T00:52:39.004008"
    },
    "KUP": {
      "code": "KUP",
      "price": 45.205577,
      "date": "1764892800000",
      "fetchedAt": "2025-12-07T00:52:39.004449"
    },
    "KH1": {
      "code": "KH1",
      "price": 0.943999,
      "date": "1764892800000",
      "fetchedAt": "2025-12-07T00:52:39.004568"
    },
    "ALC": {
      "code": "ALC",
      "price": 0.274278,
      "date": "1764892800000",
      "fetchedAt": "2025-12-07T00:52:39.006351"
    },
    "KNP": {
      "code": "KNP",
      "price": 72.895661,
      "date": "1764892800000",
      "fetchedAt": "2025-12-07T00:52:39.008184"
    },
    "PAP": {
      "code": "PAP",
      "price": 58.01867,
      "date": "1764892800000",
      "fetchedAt": "2025-12-07T00:52:39.012667"
    },
    "AIM": {
      "code": "AIM",
      "price": 19.286543,
      "date": "1764892800000",
      "fetchedAt": "2025-12-07T00:52:39.012672"
    },
    "KNZ": {
      "code": "KNZ",
      "price": 61.552988,
      "date": "1764892800000",
      "fetchedAt": "2025-12-07T00:52:39.026026"
    },
    "ADE": {
      "code": "ADE",
      "price": 0.78116,
      "date": "1764892800000",
      "fetchedAt": "2025-12-07T00:52:39.029653"
    },
    "LHM": {
      "code": "LHM",
      "price": 70.328032,
      "date": "1764892800000",
      "fetchedAt": "2025-12-07T00:52:39.032501"
    },
    "ONF": {
      "code": "ONF",
      "price": 56.460603,
      "date": "1764892800000",
      "fetchedAt": "2025-12-07T00:52:39.032505"
    },
    "OBN": {
      "code": "OBN",
      "price": 50.366747,
      "date": "1764892800000",
      "fetchedAt": "2025-12-07T00:52:39.033284"
    },
    "ODN": {
      "code": "ODN",
      "price": 49.074183,
      "date": "1764892800000",
      "fetchedAt": "2025-12-07T00:52:39.042570"
    },
    "OBR": {
      "code": "OBR",
      "price": 46.663986,
      "date": "1764892800000",
      "fetchedAt": "2025-12-07T00:52:39.044341"
    },
    "URC": {
      "code": "URC",
      "price": 49.455199,
      "date": "1764892800000",
      "fetchedAt": "2025-12-07T00:52:39.074724"
    },
    "OUN": {
      "code": "OUN",
      "price": 46.90734,
      "date": "1764892800000",
      "fetchedAt": "2025-12-07T00:52:39.076802"
    },
    "KNV": {
      "code": "KNV",
      "price": 61.319327,
      "date": "1764892800000",
      "fetchedAt": "2025-12-07T00:52:39.077613"
    },
    "APT": {
      "code": "APT",
      "price": 0.136567,
      "date": "1764892800000",
      "fetchedAt": "2025-12-07T00:52:39.087397"
    },
    "PUT": {
      "code": "PUT",
      "price": 6.434124,
      "date": "1764892800000",
      "fetchedAt": "2025-12-07T00:52:39.102921"
    },
    "URM": {
      "code": "URM",
      "price": 44.337384,
      "date": "1764892800000",
      "fetchedAt": "2025-12-07T00:52:39.106471"
    },
    "OPZ": {
      "code": "OPZ",
      "price": 4.703683,
      "date": "1764892800000",
      "fetchedAt": "2025-12-07T00:52:39.107182"
    },
    "AZZ": {
      "code": "AZZ",
      "price": 54.719111,
      "date": "1764892800000",
      "fetchedAt": "2025-12-07T00:52:39.113832"
    },
    "ARP": {
      "code": "ARP",
      "price": 37.417792,
      "date": "1764892800000",
      "fetchedAt": "2025-12-07T00:52:39.127077"
    },
    "BVB": {
      "code": "BVB",
      "price": 3.494329,
      "date": "1764892800000",
      "fetchedAt": "2025-12-07T00:52:39.131456"
    },
    "AIS": {
      "code": "AIS",
      "price": 0.0819,
      "date": "1764892800000",
      "fetchedAt": "2025-12-07T00:52:39.138971"
    },
    "ALE": {
      "code": "ALE",
      "price": 10.348897,
      "date": "1764892800000",
      "fetchedAt": "2025-12-07T00:52:39.152799"
    },
    "KLI": {
      "code": "KLI",
      "price": 1.001016,
      "date": "1764892800000",
      "fetchedAt": "2025-12-07T00:52:39.155080"
    },
    "APJ": {
      "code": "APJ",
      "price": 5.629852,
      "date": "2025-12-07T00:52:39.162841",
      "fetchedAt": "2025-12-07T00:52:39.163637"
    },
    "PUV": {
      "code": "PUV",
      "price": 48.779506,
      "date": "1764892800000",
      "fetchedAt": "2025-12-07T00:52:39.163641"
    },
    "AES": {
      "code": "AES",
      "price": 0.09648,
      "date": "1764892800000",
      "fetchedAt": "2025-12-07T00:52:39.164700"
    },
    "DTZ": {
      "code": "DTZ",
      "price": 3.977782,
      "date": "1764892800000",
      "fetchedAt": "2025-12-07T00:52:39.177572"
    },
    "AIH": {
      "code": "AIH",
      "price": 13.00797,
      "date": "1764892800000",
      "fetchedAt": "2025-12-07T00:52:39.187686"
    },
    "AFS": {
      "code": "AFS",
      "price": 0.295477,
      "date": "1764892800000",
      "fetchedAt": "2025-12-07T00:52:39.190061"
    },
    "CJH": {
      "code": "CJH",
      "price": 54.333169,
      "date": "2025-12-07T00:52:39.199105",
      "fetchedAt": "2025-12-07T00:52:39.199828"
    },
    "SAS": {
      "code": "SAS",
      "price": 1.358261,
      "date": "1764892800000",
      "fetchedAt": "2025-12-07T00:52:39.200614"
    },
    "SCZ": {
      "code": "SCZ",
      "price": 1.194613,
      "date": "1764892800000",
      "fetchedAt": "2025-12-07T00:52:39.211584"
    },
    "CVF": {
      "code": "CVF",
      "price": 3.616379,
      "date": "1764892800000",
      "fetchedAt": "2025-12-07T00:52:39.216085"
    },
    "PPJ": {
      "code": "PPJ",
      "price": 1.404512,
      "date": "2025-12-07T00:52:39.221107",
      "fetchedAt": "2025-12-07T00:52:39.221568"
    },
    "TAR": {
      "code": "TAR",
      "price": 2.02694,
      "date": "1764892800000",
      "fetchedAt": "2025-12-07T00:52:39.225803"
    },
    "SAP": {
      "code": "SAP",
      "price": 1.41669,
      "date": "1764892800000",
      "fetchedAt": "2025-12-07T00:52:39.229503"
    },
    "ICZ": {
      "code": "ICZ",
      "price": 5.736815,
      "date": "1764892800000",
      "fetchedAt": "2025-12-07T00:52:39.236335"
    },
    "AUV": {
      "code": "AUV",
      "price": 44.376196,
      "date": "1764892800000",
      "fetchedAt": "2025-12-07T00:52:39.247359"
    },
    "ODV": {
      "code": "ODV",
      "price": 16.542659,
      "date": "1764892800000",
      "fetchedAt": "2025-12-07T00:52:39.249653"
    },
    "CVA": {
      "code": "CVA",
      "price": 3.215696,
      "date": "1764892800000",
      "fetchedAt": "2025-12-07T00:52:39.254109"
    },
    "UCP": {
      "code": "UCP",
      "price": 1.011482,
      "date": "1764892800000",
      "fetchedAt": "2025-12-07T00:52:39.259617"
    },
    "KNT": {
      "code": "KNT",
      "price": 52.279613,
      "date": "1764892800000",
      "fetchedAt": "2025-12-07T00:52:39.275529"
    },
    "AFT": {
      "code": "AFT",
      "price": 0.829367,
      "date": "1764892800000",
      "fetchedAt": "2025-12-07T00:52:39.275596"
    },
    "AJK": {
      "code": "AJK",
      "price": 55.769929,
      "date": "1764892800000",
      "fetchedAt": "2025-12-07T00:52:39.278796"
    },
    "AGC": {
      "code": "AGC",
      "price": 7.88991,
      "date": "2025-12-07T00:52:39.310682",
      "fetchedAt": "2025-12-07T00:52:39.313009"
    },
    "COT": {
      "code": "COT",
      "price": 52.517752,
      "date": "1764892800000",
      "fetchedAt": "2025-12-07T00:52:39.313016"
    },
    "AVT": {
      "code": "AVT",
      "price": 173.842638,
      "date": "2025-12-07T00:52:39.316462",
      "fetchedAt": "2025-12-07T00:52:39.317306"
    },
    "SER": {
      "code": "SER",
      "price": 50.00371,
      "date": "1764892800000",
      "fetchedAt": "2025-12-07T00:52:39.317311"
    },
    "URS": {
      "code": "URS",
      "price": 2.926793,
      "date": "2025-12-07T00:52:39.345719",
      "fetchedAt": "2025-12-07T00:52:39.346644"
    },
    "MJL": {
      "code": "MJL",
      "price": 53.880095,
      "date": "1764892800000",
      "fetchedAt": "2025-12-07T00:52:39.346649"
    },
    "MJB": {
      "code": "MJB",
      "price": 5.811084,
      "date": "1764892800000",
      "fetchedAt": "2025-12-07T00:52:39.374683"
    },
    "ONE": {
      "code": "ONE",
      "price": 1.131733,
      "date": "1764892800000",
      "fetchedAt": "2025-12-07T00:52:39.374702"
    },
    "GLG": {
      "code": "GLG",
      "price": 6.515326,
      "date": "1764892800000",
      "fetchedAt": "2025-12-07T00:52:39.403017"
    },
    "BOL": {
      "code": "BOL",
      "price": 1.37505,
      "date": "1764892800000",
      "fetchedAt": "2025-12-07T00:52:39.403022"
    },
    "AYR": {
      "code": "AYR",
      "price": 0.107414,
      "date": "2025-12-07T00:52:39.429221",
      "fetchedAt": "2025-12-07T00:52:39.430172"
    },
    "SDA": {
      "code": "SDA",
      "price": 43.584438,
      "date": "1764892800000",
      "fetchedAt": "2025-12-07T00:52:39.430178"
    },
    "ESG": {
      "code": "ESG",
      "price": 3.645601,
      "date": "1764892800000",
      "fetchedAt": "2025-12-07T00:52:39.431757"
    },
    "MJH": {
      "code": "MJH",
      "price": 5.06338,
      "date": "1764892800000",
      "fetchedAt": "2025-12-07T00:52:39.432468"
    },
    "MJG": {
      "code": "MJG",
      "price": 8.890416,
      "date": "1764892800000",
      "fetchedAt": "2025-12-07T00:52:39.465775"
    },
    "FLY": {
      "code": "FLY",
      "price": 1.392745,
      "date": "1764892800000",
      "fetchedAt": "2025-12-07T00:52:39.465781"
    },
    "MPN": {
      "code": "MPN",
      "price": 53.60792,
      "date": "1764892800000",
      "fetchedAt": "2025-12-07T00:52:39.465784"
    },
    "EYT": {
      "code": "EYT",
      "price": 2.280455,
      "date": "1764892800000",
      "fetchedAt": "2025-12-07T00:52:39.466655"
    },
    "TLK": {
      "code": "TLK",
      "price": 1.358706,
      "date": "1764892800000",
      "fetchedAt": "2025-12-07T00:52:39.494197"
    },
    "SPT": {
      "code": "SPT",
      "price": 1.638041,
      "date": "1764892800000",
      "fetchedAt": "2025-12-07T00:52:39.494755"
    },
    "MPK": {
      "code": "MPK",
      "price": 7.653052,
      "date": "1764892800000",
      "fetchedAt": "2025-12-07T00:52:39.496493"
    },
    "NKL": {
      "code": "NKL",
      "price": 2.704178,
      "date": "1764892800000",
      "fetchedAt": "2025-12-07T00:52:39.497589"
    },
    "MPF": {
      "code": "MPF",
      "price": 6.447994,
      "date": "1764892800000",
      "fetchedAt": "2025-12-07T00:52:39.497593"
    },
    "CJG": {
      "code": "CJG",
      "price": 57.614487,
      "date": "2025-12-07T00:52:39.501425",
      "fetchedAt": "2025-12-07T00:52:39.502699"
    },
    "MLS": {
      "code": "MLS",
      "price": 15.084331,
      "date": "1764892800000",
      "fetchedAt": "2025-12-07T00:52:39.542992"
    },
    "AJE": {
      "code": "AJE",
      "price": 54.598385,
      "date": "2025-12-07T00:52:39.541112",
      "fetchedAt": "2025-12-07T00:52:39.542997"
    },
    "MTS": {
      "code": "MTS",
      "price": 2.327886,
      "date": "1764892800000",
      "fetchedAt": "2025-12-07T00:52:39.542999"
    },
    "GPT": {
      "code": "GPT",
      "price": 1.90193,
      "date": "1764892800000",
      "fetchedAt": "2025-12-07T00:52:39.543002"
    },
    "IDL": {
      "code": "IDL",
      "price": 4.608508,
      "date": "1764892800000",
      "fetchedAt": "2025-12-07T00:52:39.543514"
    },
    "CYD": {
      "code": "CYD",
      "price": 50.552003,
      "date": "2025-12-07T00:52:39.549734",
      "fetchedAt": "2025-12-07T00:52:39.550219"
    },
    "BGP": {
      "code": "BGP",
      "price": 4.981997,
      "date": "2025-12-07T00:52:39.552363",
      "fetchedAt": "2025-12-07T00:52:39.553235"
    },
    "AK2": {
      "code": "AK2",
      "price": 0.479146,
      "date": "2025-12-07T00:52:39.574390",
      "fetchedAt": "2025-12-07T00:52:39.575219"
    },
    "KAC": {
      "code": "KAC",
      "price": 3.013548,
      "date": "1764892800000",
      "fetchedAt": "2025-12-07T00:52:39.576498"
    },
    "RBA": {
      "code": "RBA",
      "price": 19.078601,
      "date": "1764892800000",
      "fetchedAt": "2025-12-07T00:52:39.577929"
    },
    "CKF": {
      "code": "CKF",
      "price": 1.483588,
      "date": "1764892800000",
      "fetchedAt": "2025-12-07T00:52:39.577936"
    },
    "RTI": {
      "code": "RTI",
      "price": 2.595288,
      "date": "1764892800000",
      "fetchedAt": "2025-12-07T00:52:39.577938"
    },
    "AL4": {
      "code": "AL4",
      "price": 3.093899,
      "date": "1764892800000",
      "fetchedAt": "2025-12-07T00:52:39.577940"
    },
    "KSL": {
      "code": "KSL",
      "price": 50.081328,
      "date": "1764892800000",
      "fetchedAt": "2025-12-07T00:52:39.578536"
    },
    "KSM": {
      "code": "KSM",
      "price": 44.699756,
      "date": "1764892800000",
      "fetchedAt": "2025-12-07T00:52:39.580259"
    },
    "AL5": {
      "code": "AL5",
      "price": 47.140322,
      "date": "1764892800000",
      "fetchedAt": "2025-12-07T00:52:39.602606"
    },
    "AL7": {
      "code": "AL7",
      "price": 2.903268,
      "date": "1764892800000",
      "fetchedAt": "2025-12-07T00:52:39.603344"
    },
    "MJE": {
      "code": "MJE",
      "price": 51.081911,
      "date": "1764892800000",
      "fetchedAt": "2025-12-07T00:52:39.611866"
    },
    "PVK": {
      "code": "PVK",
      "price": 4.471878,
      "date": "1764892800000",
      "fetchedAt": "2025-12-07T00:52:39.612202"
    },
    "RBK": {
      "code": "RBK",
      "price": 7.421442,
      "date": "1764892800000",
      "fetchedAt": "2025-12-07T00:52:39.619750"
    },
    "RBV": {
      "code": "RBV",
      "price": 5.362833,
      "date": "1764892800000",
      "fetchedAt": "2025-12-07T00:52:39.624956"
    },
    "URD": {
      "code": "URD",
      "price": 42.712683,
      "date": "1764892800000",
      "fetchedAt": "2025-12-07T00:52:39.626327"
    },
    "VKI": {
      "code": "VKI",
      "price": 2.407831,
      "date": "1764892800000",
      "fetchedAt": "2025-12-07T00:52:39.640700"
    },
    "RPU": {
      "code": "RPU",
      "price": 2.842271,
      "date": "1764892800000",
      "fetchedAt": "2025-12-07T00:52:39.645977"
    },
    "STM": {
      "code": "STM",
      "price": 4.920505,
      "date": "1764892800000",
      "fetchedAt": "2025-12-07T00:52:39.656392"
    },
    "RYA": {
      "code": "RYA",
      "price": 0.989915,
      "date": "1764892800000",
      "fetchedAt": "2025-12-07T00:52:39.665659"
    },
    "AS3": {
      "code": "AS3",
      "price": 0.781547,
      "date": "1764892800000",
      "fetchedAt": "2025-12-07T00:52:39.666296"
    },
    "SLN": {
      "code": "SLN",
      "price": 0.137797,
      "date": "1764892800000",
      "fetchedAt": "2025-12-07T00:52:39.666682"
    },
    "LLA": {
      "code": "LLA",
      "price": 1.308245,
      "date": "1764892800000",
      "fetchedAt": "2025-12-07T00:52:39.682002"
    },
    "BBI": {
      "code": "BBI",
      "price": 1.133803,
      "date": "1764892800000",
      "fetchedAt": "2025-12-07T00:52:39.689317"
    },
    "ABJ": {
      "code": "ABJ",
      "price": 0.813809,
      "date": "1764892800000",
      "fetchedAt": "2025-12-07T00:52:39.691281"
    },
    "BHV": {
      "code": "BHV",
      "price": 0.533662,
      "date": "1764892800000",
      "fetchedAt": "2025-12-07T00:52:39.698974"
    },
    "BBP": {
      "code": "BBP",
      "price": 1.488358,
      "date": "1764892800000",
      "fetchedAt": "2025-12-07T00:52:39.701687"
    },
    "BFE": {
      "code": "BFE",
      "price": 1.532672,
      "date": "1764892800000",
      "fetchedAt": "2025-12-07T00:52:39.706476"
    },
    "ASJ": {
      "code": "ASJ",
      "price": 2.944495,
      "date": "2025-12-07T00:52:39.717158",
      "fetchedAt": "2025-12-07T00:52:39.717867"
    },
    "BVM": {
      "code": "BVM",
      "price": 1.313002,
      "date": "1764892800000",
      "fetchedAt": "2025-12-07T00:52:39.719502"
    },
    "HVZ": {
      "code": "HVZ",
      "price": 5.928979,
      "date": "1764892800000",
      "fetchedAt": "2025-12-07T00:52:39.719857"
    },
    "AS1": {
      "code": "AS1",
      "price": 44.49756,
      "date": "1764892800000",
      "fetchedAt": "2025-12-07T00:52:39.725499"
    },
    "DEI": {
      "code": "DEI",
      "price": 0.083447,
      "date": "1764892800000",
      "fetchedAt": "2025-12-07T00:52:39.726196"
    },
    "IHZ": {
      "code": "IHZ",
      "price": 1.063326,
      "date": "1764892800000",
      "fetchedAt": "2025-12-07T00:52:39.745454"
    },
    "LID": {
      "code": "LID",
      "price": 2.215355,
      "date": "1764892800000",
      "fetchedAt": "2025-12-07T00:52:39.747740"
    },
    "AOJ": {
      "code": "AOJ",
      "price": 1.30692,
      "date": "1764892800000",
      "fetchedAt": "2025-12-07T00:52:39.755722"
    },
    "PKE": {
      "code": "PKE",
      "price": 1.043391,
      "date": "1764892800000",
      "fetchedAt": "2025-12-07T00:52:39.755757"
    },
    "GIH": {
      "code": "GIH",
      "price": 1.788357,
      "date": "1764892800000",
      "fetchedAt": "2025-12-07T00:52:39.761079"
    },
    "DOL": {
      "code": "DOL",
      "price": 45.523967,
      "date": "2025-12-07T00:52:39.770280",
      "fetchedAt": "2025-12-07T00:52:39.772057"
    },
    "KHT": {
      "code": "KHT",
      "price": 2.053025,
      "date": "1764892800000",
      "fetchedAt": "2025-12-07T00:52:39.773463"
    },
    "KHF": {
      "code": "KHF",
      "price": 1.143142,
      "date": "1764892800000",
      "fetchedAt": "2025-12-07T00:52:39.788703"
    },
    "KKL": {
      "code": "KKL",
      "price": 1.817856,
      "date": "1764892800000",
      "fetchedAt": "2025-12-07T00:52:39.792158"
    },
    "MPS": {
      "code": "MPS",
      "price": 18.400835,
      "date": "2025-12-07T00:52:39.802316",
      "fetchedAt": "2025-12-07T00:52:39.803912"
    },
    "PRU": {
      "code": "PRU",
      "price": 2.629756,
      "date": "1764892800000",
      "fetchedAt": "2025-12-07T00:52:39.803917"
    },
    "KLS": {
      "code": "KLS",
      "price": 41.513883,
      "date": "1764892800000",
      "fetchedAt": "2025-12-07T00:52:39.804684"
    },
    "LRT": {
      "code": "LRT",
      "price": 2.769625,
      "date": "1764892800000",
      "fetchedAt": "2025-12-07T00:52:39.819788"
    },
    "PKF": {
      "code": "PKF",
      "price": 4.14098,
      "date": "1764892800000",
      "fetchedAt": "2025-12-07T00:52:39.819797"
    },
    "YCL": {
      "code": "YCL",
      "price": 8.966868,
      "date": "1764892800000",
      "fetchedAt": "2025-12-07T00:52:39.834012"
    },
    "KST": {
      "code": "KST",
      "price": 1.545163,
      "date": "1764892800000",
      "fetchedAt": "2025-12-07T00:52:39.837130"
    },
    "THV": {
      "code": "THV",
      "price": 125.692261,
      "date": "1764892800000",
      "fetchedAt": "2025-12-07T00:52:39.842700"
    },
    "AED": {
      "code": "AED",
      "price": 85.175968,
      "date": "1764892800000",
      "fetchedAt": "2025-12-07T00:52:39.847817"
    },
    "AEV": {
      "code": "AEV",
      "price": 1.421064,
      "date": "1764892800000",
      "fetchedAt": "2025-12-07T00:52:39.847823"
    },
    "SLS": {
      "code": "SLS",
      "price": 1.049078,
      "date": "1764892800000",
      "fetchedAt": "2025-12-07T00:52:39.848546"
    },
    "AAK": {
      "code": "AAK",
      "price": 30.204449,
      "date": "1764892800000",
      "fetchedAt": "2025-12-07T00:52:39.855603"
    },
    "AUT": {
      "code": "AUT",
      "price": 8.094151,
      "date": "1764892800000",
      "fetchedAt": "2025-12-07T00:52:39.860717"
    },
    "ANZ": {
      "code": "ANZ",
      "price": 18.881753,
      "date": "1764892800000",
      "fetchedAt": "2025-12-07T00:52:39.869582"
    },
    "AAS": {
      "code": "AAS",
      "price": 10.239836,
      "date": "1764892800000",
      "fetchedAt": "2025-12-07T00:52:39.872900"
    },
    "URA": {
      "code": "URA",
      "price": 1.596417,
      "date": "1764892800000",
      "fetchedAt": "2025-12-07T00:52:39.878269"
    },
    "AAV": {
      "code": "AAV",
      "price": 51.355958,
      "date": "1764892800000",
      "fetchedAt": "2025-12-07T00:52:39.878589"
    },
    "NKJ": {
      "code": "NKJ",
      "price": 12.293285,
      "date": "1764892800000",
      "fetchedAt": "2025-12-07T00:52:39.878883"
    },
    "JET": {
      "code": "JET",
      "price": 1.839525,
      "date": "1764892800000",
      "fetchedAt": "2025-12-07T00:52:39.880185"
    },
    "RBT": {
      "code": "RBT",
      "price": 5.031369,
      "date": "2025-12-07T00:52:39.885889",
      "fetchedAt": "2025-12-07T00:52:39.886660"
    },
    "AVC": {
      "code": "AVC",
      "price": 141.45883,
      "date": "1764892800000",
      "fetchedAt": "2025-12-07T00:52:39.886666"
    },
    "NDL": {
      "code": "NDL",
      "price": 1.904443,
      "date": "2025-12-07T00:52:39.908456",
      "fetchedAt": "2025-12-07T00:52:39.908709"
    },
    "AYA": {
      "code": "AYA",
      "price": 16.173016,
      "date": "1764892800000",
      "fetchedAt": "2025-12-07T00:52:39.941627"
    },
    "DGH": {
      "code": "DGH",
      "price": 8.144107,
      "date": "1764892800000",
      "fetchedAt": "2025-12-07T00:52:39.948873"
    },
    "TLZ": {
      "code": "TLZ",
      "price": 13.597373,
      "date": "1764892800000",
      "fetchedAt": "2025-12-07T00:52:39.958304"
    },
    "AAL": {
      "code": "AAL",
      "price": 2.740035,
      "date": "1764892800000",
      "fetchedAt": "2025-12-07T00:52:39.958312"
    },
    "RTG": {
      "code": "RTG",
      "price": 3.985185,
      "date": "1764892800000",
      "fetchedAt": "2025-12-07T00:52:39.959373"
    },
    "RSF": {
      "code": "RSF",
      "price": 3.402927,
      "date": "1764892800000",
      "fetchedAt": "2025-12-07T00:52:39.968270"
    },
    "DEF": {
      "code": "DEF",
      "price": 2.182628,
      "date": "2025-12-07T00:52:39.972082",
      "fetchedAt": "2025-12-07T00:52:39.972301"
    },
    "YLC": {
      "code": "YLC",
      "price": 2.990578,
      "date": "1764892800000",
      "fetchedAt": "2025-12-07T00:52:39.976520"
    },
    "NKK": {
      "code": "NKK",
      "price": 6.735017,
      "date": "1764892800000",
      "fetchedAt": "2025-12-07T00:52:39.977948"
    },
    "LGO": {
      "code": "LGO",
      "price": 5.31254,
      "date": "1764892800000",
      "fetchedAt": "2025-12-07T00:52:39.984729"
    },
    "ESN": {
      "code": "ESN",
      "price": 1.384262,
      "date": "2025-12-07T00:52:39.987784",
      "fetchedAt": "2025-12-07T00:52:39.988177"
    },
    "AP2": {
      "code": "AP2",
      "price": 3.048674,
      "date": "1764892800000",
      "fetchedAt": "2025-12-07T00:52:39.997248"
    },
    "TAL": {
      "code": "TAL",
      "price": 2.458508,
      "date": "1764892800000",
      "fetchedAt": "2025-12-07T00:52:39.997254"
    },
    "AP5": {
      "code": "AP5",
      "price": 1.02061,
      "date": "1764892800000",
      "fetchedAt": "2025-12-07T00:52:39.997257"
    },
    "BSH": {
      "code": "BSH",
      "price": 0.993292,
      "date": "1764892800000",
      "fetchedAt": "2025-12-07T00:52:39.997260"
    },
    "BTZ": {
      "code": "BTZ",
      "price": 1.11075,
      "date": "1764892800000",
      "fetchedAt": "2025-12-07T00:52:39.999845"
    },
    "BAC": {
      "code": "BAC",
      "price": 2.690747,
      "date": "1764892800000",
      "fetchedAt": "2025-12-07T00:52:40.001598"
    },
    "AHI": {
      "code": "AHI",
      "price": 30.19262,
      "date": "1764892800000",
      "fetchedAt": "2025-12-07T00:52:40.002347"
    },
    "AHU": {
      "code": "AHU",
      "price": 8.811163,
      "date": "1764892800000",
      "fetchedAt": "2025-12-07T00:52:40.003503"
    },
    "AP4": {
      "code": "AP4",
      "price": 0.998264,
      "date": "1764892800000",
      "fetchedAt": "2025-12-07T00:52:40.010585"
    },
    "ABG": {
      "code": "ABG",
      "price": 29.725218,
      "date": "1764892800000",
      "fetchedAt": "2025-12-07T00:52:40.012788"
    },
    "SSE": {
      "code": "SSE",
      "price": 0.003557,
      "date": "1764892800000",
      "fetchedAt": "2025-12-07T00:52:40.023411"
    },
    "KHJ": {
      "code": "KHJ",
      "price": 0.911853,
      "date": "1764892800000",
      "fetchedAt": "2025-12-07T00:52:40.026461"
    },
    "PFS": {
      "code": "PFS",
      "price": 2.282075,
      "date": "1764892800000",
      "fetchedAt": "2025-12-07T00:52:40.026466"
    },
    "KHD": {
      "code": "KHD",
      "price": 0.890917,
      "date": "1764892800000",
      "fetchedAt": "2025-12-07T00:52:40.028164"
    },
    "BTJ": {
      "code": "BTJ",
      "price": 1.111556,
      "date": "1764892800000",
      "fetchedAt": "2025-12-07T00:52:40.028322"
    },
    "PSE": {
      "code": "PSE",
      "price": 1.34512,
      "date": "1764892800000",
      "fetchedAt": "2025-12-07T00:52:40.032903"
    },
    "LAI": {
      "code": "LAI",
      "price": 2.820783,
      "date": "1764892800000",
      "fetchedAt": "2025-12-07T00:52:40.034778"
    },
    "KLH": {
      "code": "KLH",
      "price": 2.159481,
      "date": "1764892800000",
      "fetchedAt": "2025-12-07T00:52:40.037733"
    },
    "SNY": {
      "code": "SNY",
      "price": 1.244597,
      "date": "1764892800000",
      "fetchedAt": "2025-12-07T00:52:40.038285"
    },
    "ZVB": {
      "code": "ZVB",
      "price": 57.881627,
      "date": "1764892800000",
      "fetchedAt": "2025-12-07T00:52:40.049962"
    },
    "DFI": {
      "code": "DFI",
      "price": 2.481696,
      "date": "1764892800000",
      "fetchedAt": "2025-12-07T00:52:40.050509"
    },
    "STI": {
      "code": "STI",
      "price": 1.028296,
      "date": "1764892800000",
      "fetchedAt": "2025-12-07T00:52:40.050906"
    },
    "GCD": {
      "code": "GCD",
      "price": 1.889104,
      "date": "1764892800000",
      "fetchedAt": "2025-12-07T00:52:40.058672"
    },
    "AHN": {
      "code": "AHN",
      "price": 62.409471,
      "date": "1764892800000",
      "fetchedAt": "2025-12-07T00:52:40.058679"
    },
    "BDC": {
      "code": "BDC",
      "price": 9.384152,
      "date": "1764892800000",
      "fetchedAt": "2025-12-07T00:52:40.062235"
    },
    "UHS": {
      "code": "UHS",
      "price": 2.131202,
      "date": "1764892800000",
      "fetchedAt": "2025-12-07T00:52:40.062241"
    },
    "GLM": {
      "code": "GLM",
      "price": 0.634794,
      "date": "1764892800000",
      "fetchedAt": "2025-12-07T00:52:40.063274"
    },
    "PPT": {
      "code": "PPT",
      "price": 2.424598,
      "date": "1764892800000",
      "fetchedAt": "2025-12-07T00:52:40.063279"
    },
    "IYB": {
      "code": "IYB",
      "price": 4.61735,
      "date": "1764892800000",
      "fetchedAt": "2025-12-07T00:52:40.063622"
    },
    "ESP": {
      "code": "ESP",
      "price": 0.925102,
      "date": "1764892800000",
      "fetchedAt": "2025-12-07T00:52:40.069972"
    },
    "DLN": {
      "code": "DLN",
      "price": 1.674691,
      "date": "1764892800000",
      "fetchedAt": "2025-12-07T00:52:40.070320"
    },
    "TLH": {
      "code": "TLH",
      "price": 23.63948,
      "date": "1764892800000",
      "fetchedAt": "2025-12-07T00:52:40.071259"
    },
    "IHA": {
      "code": "IHA",
      "price": 2.544093,
      "date": "2025-12-07T00:52:40.074410",
      "fetchedAt": "2025-12-07T00:52:40.074857"
    },
    "TPV": {
      "code": "TPV",
      "price": 10.102218,
      "date": "1764892800000",
      "fetchedAt": "2025-12-07T00:52:40.077246"
    },
    "JUP": {
      "code": "JUP",
      "price": 0.487993,
      "date": "1764892800000",
      "fetchedAt": "2025-12-07T00:52:40.078480"
    },
    "MTL": {
      "code": "MTL",
      "price": 1.607036,
      "date": "1764892800000",
      "fetchedAt": "2025-12-07T00:52:40.079077"
    },
    "TLE": {
      "code": "TLE",
      "price": 23.436288,
      "date": "1764892800000",
      "fetchedAt": "2025-12-07T00:52:40.083846"
    },
    "PRH": {
      "code": "PRH",
      "price": 1.671827,
      "date": "1764892800000",
      "fetchedAt": "2025-12-07T00:52:40.084565"
    },
    "SPD": {
      "code": "SPD",
      "price": 70.863564,
      "date": "1764892800000",
      "fetchedAt": "2025-12-07T00:52:40.087812"
    },
    "TKH": {
      "code": "TKH",
      "price": 1.805098,
      "date": "1764892800000",
      "fetchedAt": "2025-12-07T00:52:40.089210"
    },
    "HVT": {
      "code": "HVT",
      "price": 3.509209,
      "date": "2025-12-07T00:52:40.092264",
      "fetchedAt": "2025-12-07T00:52:40.092684"
    },
    "SPA": {
      "code": "SPA",
      "price": 58.184552,
      "date": "1764892800000",
      "fetchedAt": "2025-12-07T00:52:40.093714"
    },
    "FRA": {
      "code": "FRA",
      "price": 28.583825,
      "date": "1764892800000",
      "fetchedAt": "2025-12-07T00:52:40.093718"
    },
    "GLS": {
      "code": "GLS",
      "price": 0.130951,
      "date": "1764892800000",
      "fetchedAt": "2025-12-07T00:52:40.097204"
    },
    "DTP": {
      "code": "DTP",
      "price": 1.6937,
      "date": "1764892800000",
      "fetchedAt": "2025-12-07T00:52:40.097209"
    },
    "PAC": {
      "code": "PAC",
      "price": 2.818276,
      "date": "1764892800000",
      "fetchedAt": "2025-12-07T00:52:40.097211"
    },
    "PUA": {
      "code": "PUA",
      "price": 7.432464,
      "date": "1764892800000",
      "fetchedAt": "2025-12-07T00:52:40.099412"
    },
    "SPE": {
      "code": "SPE",
      "price": 90.063534,
      "date": "1764892800000",
      "fetchedAt": "2025-12-07T00:52:40.102889"
    },
    "SFS": {
      "code": "SFS",
      "price": 1.076035,
      "date": "1764892800000",
      "fetchedAt": "2025-12-07T00:52:40.107465"
    },
    "GP1": {
      "code": "GP1",
      "price": 3.162894,
      "date": "1764892800000",
      "fetchedAt": "2025-12-07T00:52:40.107470"
    },
    "THS": {
      "code": "THS",
      "price": 55.030331,
      "date": "1764892800000",
      "fetchedAt": "2025-12-07T00:52:40.107473"
    },
    "PPF": {
      "code": "PPF",
      "price": 3.92567,
      "date": "1764892800000",
      "fetchedAt": "2025-12-07T00:52:40.109218"
    },
    "KMF": {
      "code": "KMF",
      "price": 2.948311,
      "date": "1764892800000",
      "fetchedAt": "2025-12-07T00:52:40.114752"
    },
    "RKL": {
      "code": "RKL",
      "price": 2.463134,
      "date": "1764892800000",
      "fetchedAt": "2025-12-07T00:52:40.114757"
    },
    "SRA": {
      "code": "SRA",
      "price": 13.673689,
      "date": "1764892800000",
      "fetchedAt": "2025-12-07T00:52:40.122320"
    },
    "FYZ": {
      "code": "FYZ",
      "price": 5.046258,
      "date": "1764892800000",
      "fetchedAt": "2025-12-07T00:52:40.123276"
    },
    "NTB": {
      "code": "NTB",
      "price": 4.541219,
      "date": "1764892800000",
      "fetchedAt": "2025-12-07T00:52:40.123283"
    },
    "BFT": {
      "code": "BFT",
      "price": 1.069433,
      "date": "1764892800000",
      "fetchedAt": "2025-12-07T00:52:40.126319"
    },
    "VFS": {
      "code": "VFS",
      "price": 1.735907,
      "date": "1764892800000",
      "fetchedAt": "2025-12-07T00:52:40.126326"
    },
    "UHL": {
      "code": "UHL",
      "price": 63.28146,
      "date": "1764892800000",
      "fetchedAt": "2025-12-07T00:52:40.126328"
    },
    "AHZ": {
      "code": "AHZ",
      "price": 22.564943,
      "date": "1764892800000",
      "fetchedAt": "2025-12-07T00:52:40.126330"
    },
    "BAO": {
      "code": "BAO",
      "price": 2.695786,
      "date": "1764892800000",
      "fetchedAt": "2025-12-07T00:52:40.131792"
    },
    "BGH": {
      "code": "BGH",
      "price": 1.880038,
      "date": "1764892800000",
      "fetchedAt": "2025-12-07T00:52:40.131797"
    },
    "HJA": {
      "code": "HJA",
      "price": 17.897918,
      "date": "1764892800000",
      "fetchedAt": "2025-12-07T00:52:40.137395"
    },
    "BLG": {
      "code": "BLG",
      "price": 1.554353,
      "date": "1764892800000",
      "fetchedAt": "2025-12-07T00:52:40.137401"
    },
    "RCV": {
      "code": "RCV",
      "price": 1.297573,
      "date": "1764892800000",
      "fetchedAt": "2025-12-07T00:52:40.137404"
    },
    "AZV": {
      "code": "AZV",
      "price": 22.880258,
      "date": "1764892800000",
      "fetchedAt": "2025-12-07T00:52:40.137406"
    },
    "BIY": {
      "code": "BIY",
      "price": 1.015673,
      "date": "1764892800000",
      "fetchedAt": "2025-12-07T00:52:40.138165"
    },
    "BUT": {
      "code": "BUT",
      "price": 1.36797,
      "date": "1764892800000",
      "fetchedAt": "2025-12-07T00:52:40.149749"
    },
    "PBS": {
      "code": "PBS",
      "price": 59.081055,
      "date": "1764892800000",
      "fetchedAt": "2025-12-07T00:52:40.149758"
    },
    "BUP": {
      "code": "BUP",
      "price": 3.267824,
      "date": "1764892800000",
      "fetchedAt": "2025-12-07T00:52:40.156872"
    },
    "AII": {
      "code": "AII",
      "price": 83.121779,
      "date": "1764892800000",
      "fetchedAt": "2025-12-07T00:52:40.156880"
    },
    "TRN": {
      "code": "TRN",
      "price": 1.068619,
      "date": "1764892800000",
      "fetchedAt": "2025-12-07T00:52:40.157975"
    },
    "HUI": {
      "code": "HUI",
      "price": 78.595603,
      "date": "1764892800000",
      "fetchedAt": "2025-12-07T00:52:40.157980"
    },
    "GMA": {
      "code": "GMA",
      "price": 1.620786,
      "date": "1764892800000",
      "fetchedAt": "2025-12-07T00:52:40.158617"
    },
    "ATJ": {
      "code": "ATJ",
      "price": 17.535705,
      "date": "1764892800000",
      "fetchedAt": "2025-12-07T00:52:40.163477"
    },
    "AHH": {
      "code": "AHH",
      "price": 8.256678,
      "date": "1764892800000",
      "fetchedAt": "2025-12-07T00:52:40.170719"
    },
    "DZP": {
      "code": "DZP",
      "price": 52.217307,
      "date": "1764892800000",
      "fetchedAt": "2025-12-07T00:52:40.178973"
    },
    "DFO": {
      "code": "DFO",
      "price": 2.657854,
      "date": "1764892800000",
      "fetchedAt": "2025-12-07T00:52:40.178981"
    },
    "AHV": {
      "code": "AHV",
      "price": 16.374468,
      "date": "1764892800000",
      "fetchedAt": "2025-12-07T00:52:40.178984"
    },
    "HIZ": {
      "code": "HIZ",
      "price": 1.530348,
      "date": "1764892800000",
      "fetchedAt": "2025-12-07T00:52:40.179348"
    },
    "VCG": {
      "code": "VCG",
      "price": 4.380862,
      "date": "1764892800000",
      "fetchedAt": "2025-12-07T00:52:40.179737"
    },
    "FDV": {
      "code": "FDV",
      "price": 4.142321,
      "date": "1764892800000",
      "fetchedAt": "2025-12-07T00:52:40.182769"
    },
    "UFH": {
      "code": "UFH",
      "price": 62.485561,
      "date": "1764892800000",
      "fetchedAt": "2025-12-07T00:52:40.184468"
    },
    "EHS": {
      "code": "EHS",
      "price": 2.341695,
      "date": "1764892800000",
      "fetchedAt": "2025-12-07T00:52:40.186026"
    },
    "FYB": {
      "code": "FYB",
      "price": 84.799715,
      "date": "1764892800000",
      "fetchedAt": "2025-12-07T00:52:40.186492"
    },
    "IJF": {
      "code": "IJF",
      "price": 8.437941,
      "date": "1764892800000",
      "fetchedAt": "2025-12-07T00:52:40.186933"
    },
    "GBZ": {
      "code": "GBZ",
      "price": 2.697929,
      "date": "1764892800000",
      "fetchedAt": "2025-12-07T00:52:40.191110"
    },
    "FNE": {
      "code": "FNE",
      "price": 2.754124,
      "date": "1764892800000",
      "fetchedAt": "2025-12-07T00:52:40.191763"
    },
    "AIR": {
      "code": "AIR",
      "price": 142.240168,
      "date": "1764892800000",
      "fetchedAt": "2025-12-07T00:52:40.193007"
    },
    "FRZ": {
      "code": "FRZ",
      "price": 13.269461,
      "date": "1764892800000",
      "fetchedAt": "2025-12-07T00:52:40.197481"
    },
    "BVT": {
      "code": "BVT",
      "price": 4.14872,
      "date": "1764892800000",
      "fetchedAt": "2025-12-07T00:52:40.203281"
    },
    "GSL": {
      "code": "GSL",
      "price": 2.723652,
      "date": "1764892800000",
      "fetchedAt": "2025-12-07T00:52:40.206079"
    },
    "GSG": {
      "code": "GSG",
      "price": 61.894351,
      "date": "1764892800000",
      "fetchedAt": "2025-12-07T00:52:40.206597"
    },
    "CBO": {
      "code": "CBO",
      "price": 192.922699,
      "date": "1764892800000",
      "fetchedAt": "2025-12-07T00:52:40.207036"
    },
    "HPJ": {
      "code": "HPJ",
      "price": 3.497811,
      "date": "1764892800000",
      "fetchedAt": "2025-12-07T00:52:40.211930"
    },
    "GMO": {
      "code": "GMO",
      "price": 2.982967,
      "date": "1764892800000",
      "fetchedAt": "2025-12-07T00:52:40.213098"
    },
    "OMG": {
      "code": "OMG",
      "price": 1.33054,
      "date": "1764892800000",
      "fetchedAt": "2025-12-07T00:52:40.216588"
    },
    "PRF": {
      "code": "PRF",
      "price": 54.358885,
      "date": "1764892800000",
      "fetchedAt": "2025-12-07T00:52:40.217362"
    },
    "NOV": {
      "code": "NOV",
      "price": 49.046201,
      "date": "1764892800000",
      "fetchedAt": "2025-12-07T00:52:40.217821"
    },
    "KNI": {
      "code": "KNI",
      "price": 1.062511,
      "date": "1764892800000",
      "fetchedAt": "2025-12-07T00:52:40.224961"
    },
    "LGK": {
      "code": "LGK",
      "price": 1.108205,
      "date": "1764892800000",
      "fetchedAt": "2025-12-07T00:52:40.226267"
    },
    "KSK": {
      "code": "KSK",
      "price": 2.232343,
      "date": "1764892800000",
      "fetchedAt": "2025-12-07T00:52:40.226272"
    },
    "VCD": {
      "code": "VCD",
      "price": 4.675682,
      "date": "1764892800000",
      "fetchedAt": "2025-12-07T00:52:40.226275"
    },
    "LZV": {
      "code": "LZV",
      "price": 10.644841,
      "date": "1764892800000",
      "fetchedAt": "2025-12-07T00:52:40.233641"
    },
    "IZA": {
      "code": "IZA",
      "price": 1.674795,
      "date": "1764892800000",
      "fetchedAt": "2025-12-07T00:52:40.235151"
    },
    "IDI": {
      "code": "IDI",
      "price": 1.162534,
      "date": "1764892800000",
      "fetchedAt": "2025-12-07T00:52:40.235157"
    },
    "EJG": {
      "code": "EJG",
      "price": 8.253317,
      "date": "1764892800000",
      "fetchedAt": "2025-12-07T00:52:40.235159"
    },
    "HYP": {
      "code": "HYP",
      "price": 8.121284,
      "date": "1764892800000",
      "fetchedAt": "2025-12-07T00:52:40.242017"
    },
    "SPN": {
      "code": "SPN",
      "price": 7.994455,
      "date": "1764892800000",
      "fetchedAt": "2025-12-07T00:52:40.242661"
    },
    "IZM": {
      "code": "IZM",
      "price": 1.769236,
      "date": "1764892800000",
      "fetchedAt": "2025-12-07T00:52:40.244016"
    },
    "KTI": {
      "code": "KTI",
      "price": 1.49184,
      "date": "1764892800000",
      "fetchedAt": "2025-12-07T00:52:40.249976"
    },
    "KVS": {
      "code": "KVS",
      "price": 2.874965,
      "date": "1764892800000",
      "fetchedAt": "2025-12-07T00:52:40.249981"
    },
    "KZO": {
      "code": "KZO",
      "price": 1.765405,
      "date": "1764892800000",
      "fetchedAt": "2025-12-07T00:52:40.252066"
    },
    "PTG": {
      "code": "PTG",
      "price": 53.964411,
      "date": "1764892800000",
      "fetchedAt": "2025-12-07T00:52:40.256830"
    },
    "KOT": {
      "code": "KOT",
      "price": 1.189014,
      "date": "1764892800000",
      "fetchedAt": "2025-12-07T00:52:40.257368"
    },
    "SYF": {
      "code": "SYF",
      "price": 190.525618,
      "date": "1764892800000",
      "fetchedAt": "2025-12-07T00:52:40.262047"
    },
    "PUZ": {
      "code": "PUZ",
      "price": 7.624997,
      "date": "1764892800000",
      "fetchedAt": "2025-12-07T00:52:40.273423"
    },
    "MSK": {
      "code": "MSK",
      "price": 3.047519,
      "date": "1764892800000",
      "fetchedAt": "2025-12-07T00:52:40.277141"
    },
    "MTI": {
      "code": "MTI",
      "price": 0.018461,
      "date": "1764892800000",
      "fetchedAt": "2025-12-07T00:52:40.281499"
    },
    "MCU": {
      "code": "MCU",
      "price": 1.073951,
      "date": "1764892800000",
      "fetchedAt": "2025-12-07T00:52:40.284204"
    },
    "NLD": {
      "code": "NLD",
      "price": 46.845283,
      "date": "1764892800000",
      "fetchedAt": "2025-12-07T00:52:40.284369"
    },
    "DOR": {
      "code": "DOR",
      "price": 61.226656,
      "date": "1764892800000",
      "fetchedAt": "2025-12-07T00:52:40.286449"
    },
    "OTM": {
      "code": "OTM",
      "price": 1.233669,
      "date": "1764892800000",
      "fetchedAt": "2025-12-07T00:52:40.291298"
    },
    "ORI": {
      "code": "ORI",
      "price": 52.641803,
      "date": "1764892800000",
      "fetchedAt": "2025-12-07T00:52:40.293560"
    },
    "PNR": {
      "code": "PNR",
      "price": 1.541964,
      "date": "1764892800000",
      "fetchedAt": "2025-12-07T00:52:40.297919"
    },
    "PGS": {
      "code": "PGS",
      "price": 1.072952,
      "date": "1764892800000",
      "fetchedAt": "2025-12-07T00:52:40.297925"
    },
    "PPZ": {
      "code": "PPZ",
      "price": 5.031018,
      "date": "1764892800000",
      "fetchedAt": "2025-12-07T00:52:40.297928"
    },
    "FYG": {
      "code": "FYG",
      "price": 14.557437,
      "date": "1764892800000",
      "fetchedAt": "2025-12-07T00:52:40.298499"
    },
    "SAT": {
      "code": "SAT",
      "price": 195.975994,
      "date": "1764892800000",
      "fetchedAt": "2025-12-07T00:52:40.302788"
    },
    "PSS": {
      "code": "PSS",
      "price": 4.640892,
      "date": "1764892800000",
      "fetchedAt": "2025-12-07T00:52:40.304902"
    },
    "GNK": {
      "code": "GNK",
      "price": 58.095485,
      "date": "1764892800000",
      "fetchedAt": "2025-12-07T00:52:40.304909"
    },
    "SRE": {
      "code": "SRE",
      "price": 54.963604,
      "date": "1764892800000",
      "fetchedAt": "2025-12-07T00:52:40.307809"
    },
    "SVS": {
      "code": "SVS",
      "price": 2.099842,
      "date": "1764892800000",
      "fetchedAt": "2025-12-07T00:52:40.309443"
    },
    "SRO": {
      "code": "SRO",
      "price": 22.088977,
      "date": "1764892800000",
      "fetchedAt": "2025-12-07T00:52:40.309787"
    },
    "SYL": {
      "code": "SYL",
      "price": 3663.935906,
      "date": "1764892800000",
      "fetchedAt": "2025-12-07T00:52:40.311132"
    },
    "TAZ": {
      "code": "TAZ",
      "price": 1.820941,
      "date": "1764892800000",
      "fetchedAt": "2025-12-07T00:52:40.313151"
    },
    "TEJ": {
      "code": "TEJ",
      "price": 1.836752,
      "date": "1764892800000",
      "fetchedAt": "2025-12-07T00:52:40.316184"
    },
    "TJL": {
      "code": "TJL",
      "price": 17.966238,
      "date": "1764892800000",
      "fetchedAt": "2025-12-07T00:52:40.319006"
    },
    "TMU": {
      "code": "TMU",
      "price": 1.108861,
      "date": "1764892800000",
      "fetchedAt": "2025-12-07T00:52:40.323888"
    },
    "TSP": {
      "code": "TSP",
      "price": 60.356466,
      "date": "1764892800000",
      "fetchedAt": "2025-12-07T00:52:40.324512"
    },
    "FYM": {
      "code": "FYM",
      "price": 0.37996,
      "date": "1764892800000",
      "fetchedAt": "2025-12-07T00:52:40.329500"
    },
    "USS": {
      "code": "USS",
      "price": 2.891097,
      "date": "1764892800000",
      "fetchedAt": "2025-12-07T00:52:40.329504"
    },
    "GBC": {
      "code": "GBC",
      "price": 0.248507,
      "date": "1764892800000",
      "fetchedAt": "2025-12-07T00:52:40.329507"
    },
    "VTF": {
      "code": "VTF",
      "price": 1.747565,
      "date": "1764892800000",
      "fetchedAt": "2025-12-07T00:52:40.329509"
    },
    "YPR": {
      "code": "YPR",
      "price": 1.243988,
      "date": "1764892800000",
      "fetchedAt": "2025-12-07T00:52:40.330391"
    },
    "PYH": {
      "code": "PYH",
      "price": 5.984768,
      "date": "1764892800000",
      "fetchedAt": "2025-12-07T00:52:40.333255"
    },
    "PYL": {
      "code": "PYL",
      "price": 7.32549,
      "date": "1764892800000",
      "fetchedAt": "2025-12-07T00:52:40.339207"
    },
    "HMT": {
      "code": "HMT",
      "price": 6.278984,
      "date": "1764892800000",
      "fetchedAt": "2025-12-07T00:52:40.339213"
    },
    "PYF": {
      "code": "PYF",
      "price": 7.439314,
      "date": "1764892800000",
      "fetchedAt": "2025-12-07T00:52:40.339215"
    },
    "BJD": {
      "code": "BJD",
      "price": 46.272394,
      "date": "1764892800000",
      "fetchedAt": "2025-12-07T00:52:40.339218"
    },
    "DOD": {
      "code": "DOD",
      "price": 58.613033,
      "date": "1764892800000",
      "fetchedAt": "2025-12-07T00:52:40.343220"
    },
    "HGT": {
      "code": "HGT",
      "price": 81.877384,
      "date": "1764892800000",
      "fetchedAt": "2025-12-07T00:52:40.354033"
    },
    "IBJ": {
      "code": "IBJ",
      "price": 55.466945,
      "date": "1764892800000",
      "fetchedAt": "2025-12-07T00:52:40.354868"
    },
    "ZMU": {
      "code": "ZMU",
      "price": 1.091908,
      "date": "1764892800000",
      "fetchedAt": "2025-12-07T00:52:40.356350"
    },
    "THO": {
      "code": "THO",
      "price": 44.551415,
      "date": "1764892800000",
      "fetchedAt": "2025-12-07T00:52:40.356355"
    },
    "ZMT": {
      "code": "ZMT",
      "price": 54.624667,
      "date": "1764892800000",
      "fetchedAt": "2025-12-07T00:52:40.357150"
    },
    "DVU": {
      "code": "DVU",
      "price": 6.223417,
      "date": "1764892800000",
      "fetchedAt": "2025-12-07T00:52:40.360328"
    },
    "FDZ": {
      "code": "FDZ",
      "price": 0.264344,
      "date": "1764892800000",
      "fetchedAt": "2025-12-07T00:52:40.365884"
    },
    "IOT": {
      "code": "IOT",
      "price": 49.870701,
      "date": "1764892800000",
      "fetchedAt": "2025-12-07T00:52:40.365891"
    },
    "YDM": {
      "code": "YDM",
      "price": 1.340848,
      "date": "1764892800000",
      "fetchedAt": "2025-12-07T00:52:40.367353"
    },
    "SYR": {
      "code": "SYR",
      "price": 44.313837,
      "date": "1764892800000",
      "fetchedAt": "2025-12-07T00:52:40.367358"
    },
    "FYI": {
      "code": "FYI",
      "price": 6.831629,
      "date": "1764892800000",
      "fetchedAt": "2025-12-07T00:52:40.368491"
    },
    "AY7": {
      "code": "AY7",
      "price": 1.217999,
      "date": "1764892800000",
      "fetchedAt": "2025-12-07T00:52:40.374405"
    },
    "AY6": {
      "code": "AY6",
      "price": 1.096136,
      "date": "1764892800000",
      "fetchedAt": "2025-12-07T00:52:40.374412"
    },
    "PSL": {
      "code": "PSL",
      "price": 7.081302,
      "date": "1764892800000",
      "fetchedAt": "2025-12-07T00:52:40.375166"
    },
    "GSE": {
      "code": "GSE",
      "price": 55.416039,
      "date": "1764892800000",
      "fetchedAt": "2025-12-07T00:52:40.376716"
    },
    "PSG": {
      "code": "PSG",
      "price": 10.587141,
      "date": "1764892800000",
      "fetchedAt": "2025-12-07T00:52:40.378250"
    },
    "GL1": {
      "code": "GL1",
      "price": 1137.567794,
      "date": "1764892800000",
      "fetchedAt": "2025-12-07T00:52:40.381911"
    },
    "GTF": {
      "code": "GTF",
      "price": 12.118524,
      "date": "1764892800000",
      "fetchedAt": "2025-12-07T00:52:40.381918"
    },
    "GSP": {
      "code": "GSP",
      "price": 0.404185,
      "date": "1764892800000",
      "fetchedAt": "2025-12-07T00:52:40.382381"
    },
    "GBL": {
      "code": "GBL",
      "price": 0.664768,
      "date": "1764892800000",
      "fetchedAt": "2025-12-07T00:52:40.384043"
    },
    "IBG": {
      "code": "IBG",
      "price": 1.257094,
      "date": "1764892800000",
      "fetchedAt": "2025-12-07T00:52:40.384420"
    },
    "YBJ": {
      "code": "YBJ",
      "price": 50.488206,
      "date": "1764892800000",
      "fetchedAt": "2025-12-07T00:52:40.388964"
    },
    "IBR": {
      "code": "IBR",
      "price": 0.227528,
      "date": "1764892800000",
      "fetchedAt": "2025-12-07T00:52:40.391719"
    },
    "AU1": {
      "code": "AU1",
      "price": 1.013094,
      "date": "1764892800000",
      "fetchedAt": "2025-12-07T00:52:40.392018"
    },
    "FYH": {
      "code": "FYH",
      "price": 75.717984,
      "date": "1764892800000",
      "fetchedAt": "2025-12-07T00:52:40.400044"
    },
    "CBD": {
      "code": "CBD",
      "price": 0.569862,
      "date": "1764892800000",
      "fetchedAt": "2025-12-07T00:52:40.403136"
    },
    "CVL": {
      "code": "CVL",
      "price": 1.028053,
      "date": "1764892800000",
      "fetchedAt": "2025-12-07T00:52:40.403143"
    },
    "AZJ": {
      "code": "AZJ",
      "price": 15.00791,
      "date": "1764892800000",
      "fetchedAt": "2025-12-07T00:52:40.405445"
    },
    "BON": {
      "code": "BON",
      "price": 1.158328,
      "date": "1764892800000",
      "fetchedAt": "2025-12-07T00:52:40.405454"
    },
    "DGF": {
      "code": "DGF",
      "price": 1.076027,
      "date": "1764892800000",
      "fetchedAt": "2025-12-07T00:52:40.411110"
    },
    "DNF": {
      "code": "DNF",
      "price": 1.000426,
      "date": "1764892800000",
      "fetchedAt": "2025-12-07T00:52:40.411117"
    },
    "CAH": {
      "code": "CAH",
      "price": 1.026029,
      "date": "1764892800000",
      "fetchedAt": "2025-12-07T00:52:40.411732"
    },
    "HFR": {
      "code": "HFR",
      "price": 1.166303,
      "date": "1764892800000",
      "fetchedAt": "2025-12-07T00:52:40.413158"
    },
    "AJ1": {
      "code": "AJ1",
      "price": 1.084781,
      "date": "1764892800000",
      "fetchedAt": "2025-12-07T00:52:40.419458"
    },
    "P1A": {
      "code": "P1A",
      "price": 1.132265,
      "date": "1764892800000",
      "fetchedAt": "2025-12-07T00:52:40.419469"
    },
    "PAB": {
      "code": "PAB",
      "price": 1.058696,
      "date": "1764892800000",
      "fetchedAt": "2025-12-07T00:52:40.419979"
    },
    "DA1": {
      "code": "DA1",
      "price": 43.27276,
      "date": "1764892800000",
      "fetchedAt": "2025-12-07T00:52:40.428665"
    },
    "BOS": {
      "code": "BOS",
      "price": 1.364829,
      "date": "1764892800000",
      "fetchedAt": "2025-12-07T00:52:40.431440"
    },
    "BLA": {
      "code": "BLA",
      "price": 11.914104,
      "date": "1764892800000",
      "fetchedAt": "2025-12-07T00:52:40.432014"
    },
    "BRB": {
      "code": "BRB",
      "price": 0.813062,
      "date": "1764892800000",
      "fetchedAt": "2025-12-07T00:52:40.441170"
    },
    "BOH": {
      "code": "BOH",
      "price": 1.126462,
      "date": "1764892800000",
      "fetchedAt": "2025-12-07T00:52:40.443067"
    },
    "BBO": {
      "code": "BBO",
      "price": 1.123123,
      "date": "1764892800000",
      "fetchedAt": "2025-12-07T00:52:40.446235"
    },
    "BLT": {
      "code": "BLT",
      "price": 1.45848,
      "date": "1764892800000",
      "fetchedAt": "2025-12-07T00:52:40.447579"
    },
    "BP5": {
      "code": "BP5",
      "price": 1.306829,
      "date": "1764892800000",
      "fetchedAt": "2025-12-07T00:52:40.454622"
    },
    "CVC": {
      "code": "CVC",
      "price": 2.214057,
      "date": "2025-12-07T00:52:40.460542",
      "fetchedAt": "2025-12-07T00:52:40.461508"
    },
    "BBN": {
      "code": "BBN",
      "price": 0.830614,
      "date": "1764892800000",
      "fetchedAt": "2025-12-07T00:52:40.467532"
    },
    "BPD": {
      "code": "BPD",
      "price": 43.975216,
      "date": "1764892800000",
      "fetchedAt": "2025-12-07T00:52:40.489450"
    },
    "BDO": {
      "code": "BDO",
      "price": 2.316502,
      "date": "1764892800000",
      "fetchedAt": "2025-12-07T00:52:40.497096"
    },
    "BBS": {
      "code": "BBS",
      "price": 1.144055,
      "date": "1764892800000",
      "fetchedAt": "2025-12-07T00:52:40.497103"
    },
    "BCO": {
      "code": "BCO",
      "price": 1.309471,
      "date": "1764892800000",
      "fetchedAt": "2025-12-07T00:52:40.498066"
    },
    "BHA": {
      "code": "BHA",
      "price": 1.173659,
      "date": "1764892800000",
      "fetchedAt": "2025-12-07T00:52:40.501963"
    },
    "BMU": {
      "code": "BMU",
      "price": 0.713088,
      "date": "1764892800000",
      "fetchedAt": "2025-12-07T00:52:40.505139"
    },
    "BPZ": {
      "code": "BPZ",
      "price": 1.187348,
      "date": "1764892800000",
      "fetchedAt": "2025-12-07T00:52:40.510329"
    },
    "BUC": {
      "code": "BUC",
      "price": 1.047784,
      "date": "1764892800000",
      "fetchedAt": "2025-12-07T00:52:40.530148"
    },
    "BIK": {
      "code": "BIK",
      "price": 1.286819,
      "date": "1764892800000",
      "fetchedAt": "2025-12-07T00:52:40.530157"
    },
    "BUV": {
      "code": "BUV",
      "price": 1.128912,
      "date": "1764892800000",
      "fetchedAt": "2025-12-07T00:52:40.530160"
    }
  }
}